radioplayer/dataclasses/__init__.py
radioplayer/dataclasses/dataclasses.py
radioplayer/dataclasses/py.typed
radioplayer_dataclasses-0.6.0.dist-info/LICENSE
radioplayer_dataclasses-0.6.0.dist-info/METADATA
radioplayer_dataclasses-0.6.0.dist-info/WHEEL
radioplayer_dataclasses-0.6.0.dist-info/RECORD
