Metadata-Version: 2.1
Name: radioplayer-dataclasses
Version: 0.6.0
Summary: Python dataclasses for radioplayer generated from XSD
Home-page: https://github.com/radiorabe/python-radioplayer-dataclasses
License: AGPL-3
Author: RaBe IT-Reaktion
Author-email: it@rabe.ch
Requires-Python: >=3.11,<4.0
Classifier: Development Status :: 3 - Alpha
Classifier: Intended Audience :: Developers
Classifier: License :: Other/Proprietary License
Classifier: Programming Language :: Python :: 3
Classifier: Programming Language :: Python :: 3.11
Classifier: Programming Language :: Python :: 3.12
Classifier: Programming Language :: Python :: 3.10
Classifier: Programming Language :: Python :: 3.9
Classifier: Topic :: Software Development :: Libraries :: Python Modules
Requires-Dist: xsdata (>=22.12,<25.0)
Project-URL: Repository, https://github.com/radiorabe/python-radioplayer-dataclasses
